munpy/__init__.py
munpy/config.py
munpy/general.py
munpy/osm.py
munpy/postprocessing.py
munpy/copert/__init__.py
munpy/copert/copert.py
munpy/copert/emissions.py
munpy/copert/copert_params/HDV_parameter.csv
munpy/copert/copert_params/LDV_parameter.csv
munpy/copert/copert_params/Moto_parameter.csv
munpy/copert/copert_params/PC_parameter.csv
munpy/copert/copert_params/__init__.py
munpy/preprocessing/__init__.py
munpy/preprocessing/background.py
munpy/preprocessing/meteo.py
munpy/preprocessing/meteo_functions.py
munpy/preprocessing/traffic.py
lib_munpy_dev-0.0.7.dist-info/METADATA
lib_munpy_dev-0.0.7.dist-info/WHEEL
lib_munpy_dev-0.0.7.dist-info/top_level.txt
lib_munpy_dev-0.0.7.dist-info/RECORD
