Metadata-Version: 2.1
Name: lib-munpy-dev
Version: 0.0.7
Summary: Package to process MUNICH input/output data
Author-email: Libelium <n.gomariz@libelium.com>
Requires-Python: >=3.10
Requires-Dist: build ==1.0.3
Requires-Dist: cdsapi ==0.6.1
Requires-Dist: certifi ==2023.11.17
Requires-Dist: cffi ==1.16.0
Requires-Dist: cftime ==1.6.3
Requires-Dist: charset-normalizer ==3.3.2
Requires-Dist: cryptography ==42.0.2
Requires-Dist: docutils ==0.20.1
Requires-Dist: greenlet ==3.0.3
Requires-Dist: idna ==3.6
Requires-Dist: importlib-metadata ==7.0.1
Requires-Dist: jaraco.classes ==3.3.0
Requires-Dist: jeepney ==0.8.0
Requires-Dist: keyring ==24.3.0
Requires-Dist: markdown-it-py ==3.0.0
Requires-Dist: mdurl ==0.1.2
Requires-Dist: more-itertools ==10.2.0
Requires-Dist: netCDF4 ==1.6.5
Requires-Dist: nh3 ==0.2.15
Requires-Dist: numpy ==1.26.3
Requires-Dist: osmium ==3.7.0
Requires-Dist: packaging ==23.2
Requires-Dist: pandas ==2.2.0
Requires-Dist: pkginfo ==1.9.6
Requires-Dist: psycopg ==3.1.17
Requires-Dist: psycopg-binary ==3.1.17
Requires-Dist: pycparser ==2.21
Requires-Dist: Pygments ==2.17.2
Requires-Dist: pyproject-hooks ==1.0.0
Requires-Dist: python-dateutil ==2.8.2
Requires-Dist: pytz ==2023.4
Requires-Dist: PyYAML ==6.0.1
Requires-Dist: readme-renderer ==42.0
Requires-Dist: requests ==2.31.0
Requires-Dist: requests-toolbelt ==1.0.0
Requires-Dist: rfc3986 ==2.0.0
Requires-Dist: rich ==13.7.0
Requires-Dist: SecretStorage ==3.3.3
Requires-Dist: six ==1.16.0
Requires-Dist: SQLAlchemy ==2.0.2
Requires-Dist: tomli ==2.0.1
Requires-Dist: tqdm ==4.66.1
Requires-Dist: twine ==4.0.2
Requires-Dist: typing-extensions ==4.9.0
Requires-Dist: tzdata ==2023.4
Requires-Dist: urllib3 ==1.26.18
Requires-Dist: zipp ==3.17.0
